iterstrat/__init__.py
iterstrat/ml_stratifiers.py
tests/__init__.py
tests/test_ml_stratifiers.py
iterative_stratification-0.1.9.dist-info/LICENSE
iterative_stratification-0.1.9.dist-info/METADATA
iterative_stratification-0.1.9.dist-info/WHEEL
iterative_stratification-0.1.9.dist-info/top_level.txt
iterative_stratification-0.1.9.dist-info/RECORD
