Metadata-Version: 2.1
Name: iterative-stratification
Version: 0.1.9
Summary: Package that provides scikit-learn compatible cross validators with stratification for multilabel data
Home-page: https://github.com/trent-b/iterative-stratification
Download-URL: https://github.com/trent-b/iterative-stratification
Maintainer: Trent J. Bradberry
Maintainer-email: trentjason@hotmail.com
License: BSD 3
Classifier: Intended Audience :: Science/Research
Classifier: Intended Audience :: Developers
Classifier: Programming Language :: Python
Classifier: Topic :: Software Development
Classifier: Topic :: Scientific/Engineering
License-File: LICENSE
Requires-Dist: numpy
Requires-Dist: scipy
Requires-Dist: scikit-learn
